coderoller-0.4.3.dist-info/METADATA
coderoller-0.4.3.dist-info/WHEEL
coderoller-0.4.3.dist-info/entry_points.txt
coderoller-0.4.3.dist-info/licenses/LICENSE
coderoller/__init__.py
coderoller/__init__.pyi
coderoller/flatten_repo.py
coderoller/flatten_repo.pyi
coderoller/source_repo_flattener.py
coderoller/source_repo_flattener.pyi
coderoller-0.4.3.dist-info/RECORD
