Metadata-Version: 2.1
Name: coderoller
Version: 0.4.3
Summary: A collection of tools to flatten and process code repositories
Author-Email: "B.T. Franklin" <brandon.franklin@gmail.com>
License: MIT
Classifier: Programming Language :: Python :: 3
Classifier: Programming Language :: Python :: 3 :: Only
Classifier: Programming Language :: Python :: 3.10
Classifier: Programming Language :: Python :: 3.11
Classifier: Programming Language :: Python :: 3.12
Classifier: Programming Language :: Python :: 3.13
Classifier: License :: OSI Approved :: MIT License
Classifier: Operating System :: OS Independent
Classifier: Intended Audience :: Developers
Classifier: Topic :: Software Development :: Libraries :: Python Modules
Classifier: Topic :: Software Development :: Code Generators
Classifier: Topic :: Utilities
Classifier: Environment :: Console
Project-URL: Homepage, https://github.com/btfranklin/coderoller
Project-URL: Issues, https://github.com/btfranklin/coderoller/issues
Project-URL: Changelog, https://github.com/btfranklin/coderoller/releases
Project-URL: Repository, https://github.com/btfranklin/coderoller.git
Requires-Python: >=3.10
Requires-Dist: gitpython>=3.1.43
Requires-Dist: pathspec>=0.12.1
